pyrtma/__init__.py
pyrtma/__version__.py
pyrtma/client.py
pyrtma/client_logging.py
pyrtma/compile.py
pyrtma/constants.py
pyrtma/context.py
pyrtma/core_defs.py
pyrtma/exceptions.py
pyrtma/header.py
pyrtma/manager.py
pyrtma/message.py
pyrtma/message_base.py
pyrtma/message_data.py
pyrtma/parser.py
pyrtma/py.typed
pyrtma/reserved_field_names.json
pyrtma/unified_console_log.py
pyrtma/validators.py
pyrtma/web_manager.py
pyrtma/compilers/c99.py
pyrtma/compilers/info.py
pyrtma/compilers/javascript.py
pyrtma/compilers/matlab.py
pyrtma/compilers/python.py
pyrtma/compilers/python_v1.py
pyrtma/compilers/yaml.py
pyrtma/core_defs/core_defs.yaml
pyrtma/core_defs/data_logger.yaml
pyrtma/core_defs/quick_logger.yaml
pyrtma/data_logger/__init__.py
pyrtma/data_logger/__main__.py
pyrtma/data_logger/cli.py
pyrtma/data_logger/data_formatter.py
pyrtma/data_logger/data_logger.py
pyrtma/data_logger/dataset.py
pyrtma/data_logger/dataset_writer.py
pyrtma/data_logger/exceptions.py
pyrtma/data_logger/formatters/json.py
pyrtma/data_logger/formatters/msg_headers.py
pyrtma/data_logger/formatters/quicklogger.py
pyrtma/data_logger/formatters/raw.py
pyrtma/utils/generate_test_defs.py
pyrtma/utils/print.py
pyrtma/utils/quicklogger_reader.py
pyrtma/utils/random_fields.py
pyrtma-3.0.0.dist-info/licenses/LICENSE
pyrtma-3.0.0.dist-info/METADATA
pyrtma-3.0.0.dist-info/WHEEL
pyrtma-3.0.0.dist-info/entry_points.txt
pyrtma-3.0.0.dist-info/top_level.txt
pyrtma-3.0.0.dist-info/RECORD
