Metadata-Version: 2.4
Name: pyrtma
Version: 3.0.0
Summary: A Python client for RTMA/Dragonfly
Author-email: David Weir <dmw109@pitt.edu>, Jeff Weiss <jmw182@pitt.edu>, Tyler Madonna <tjm159@pitt.edu>, Tyler Simpson <tws21@pitt.edu>
Project-URL: Homepage, https://github.com/pitt-rnel/pyrtma
Project-URL: Bug Tracker, https://github.com/pitt-rnel/pyrtma/issues
Classifier: Programming Language :: Python :: 3
Classifier: License :: OSI Approved :: MIT License
Classifier: Operating System :: OS Independent
Requires-Python: >=3.10
License-File: LICENSE
Requires-Dist: ruamel.yaml
Requires-Dist: websocket-server
Requires-Dist: rich
Requires-Dist: black
Requires-Dist: packaging
Dynamic: license-file
